[
    {
        "categories": [],
        "domains": [],
        "is_key_concept": false,
        "main_sense": ""
    },
    {
        "categories": [],
        "domains": [
            "philosophy and psychology"
        ],
        "is_key_concept": true,
        "main_sense": ""
    },
    {
        "categories": [],
        "domains": [
            "religion mysticism and mythology"
        ],
        "is_key_concept": false,
        "main_sense": ""
    },
    {
        "categories": [],
        "domains": [
            "art architecture and archaeology"
        ],
        "is_key_concept": false,
        "main_sense": ""
    },
    {
        "categories": [],
        "domains": [
            "language and linguistics"
        ],
        "is_key_concept": false,
        "main_sense": ""
    },
    {
        "categories": [],
        "domains": [],
        "is_key_concept": false,
        "main_sense": ""
    },
    {
        "categories": [
            "concetti delle scienze etnoantropologiche",
            "raggruppamenti sociali",
            "sociologia della cultura"
        ],
        "domains": [
            "culture and society"
        ],
        "is_key_concept": true,
        "main_sense": ""
    },
    {
        "categories": [
            "ebraismo"
        ],
        "domains": [
            "religion mysticism and mythology"
        ],
        "is_key_concept": false,
        "main_sense": ""
    },
    {
        "categories": [
            "comunit\u00e0 ebraiche del lazio",
            "ghetti ebraici d'italia",
            "luoghi dell'olocausto in italia",
            "roma r. xi sant'angelo",
            "storia di roma nell'et\u00e0 moderna"
        ],
        "domains": [
            "religion mysticism and mythology"
        ],
        "is_key_concept": false,
        "main_sense": ""
    },
    {
        "categories": [],
        "domains": [],
        "is_key_concept": false,
        "main_sense": ""
    },
    {
        "categories": [
            "comunit\u00e0 ebraiche del lazio",
            "ghetti ebraici d'italia",
            "luoghi dell'olocausto in italia",
            "roma r. xi sant'angelo",
            "storia di roma nell'et\u00e0 moderna"
        ],
        "domains": [
            "religion mysticism and mythology"
        ],
        "is_key_concept": false,
        "main_sense": ""
    }
]