[
    {
        "categories": [],
        "domains": [],
        "is_key_concept": false,
        "main_sense": ""
    },
    {
        "categories": [
            "alpi apuane",
            "montagne della provincia di lucca",
            "montagne del subappennino toscano",
            "siti di interesse comunitario della provincia di lucca"
        ],
        "domains": [],
        "is_key_concept": false,
        "main_sense": ""
    },
    {
        "categories": [
            "satira",
            "storia della televisione"
        ],
        "domains": [],
        "is_key_concept": false,
        "main_sense": ""
    },
    {
        "categories": [
            "governo degli stati uniti d'america",
            "presidenti degli stati uniti d'america"
        ],
        "domains": [
            "politics and government",
            "royalty and nobility"
        ],
        "is_key_concept": false,
        "main_sense": ""
    },
    {
        "categories": [],
        "domains": [
            "physics and astronomy"
        ],
        "is_key_concept": false,
        "main_sense": ""
    }
]