[
    {
        "categories": [],
        "domains": [],
        "is_key_concept": false,
        "main_sense": ""
    },
    {
        "categories": [
            "numeri"
        ],
        "domains": [
            "mathematics"
        ],
        "is_key_concept": true,
        "main_sense": ""
    },
    {
        "categories": [],
        "domains": [
            "religion mysticism and mythology"
        ],
        "is_key_concept": false,
        "main_sense": ""
    },
    {
        "categories": [
            "organi degli enti territoriali d'italia"
        ],
        "domains": [],
        "is_key_concept": false,
        "main_sense": ""
    },
    {
        "categories": [],
        "domains": [],
        "is_key_concept": false,
        "main_sense": ""
    },
    {
        "categories": [],
        "domains": [],
        "is_key_concept": false,
        "main_sense": ""
    },
    {
        "categories": [
            "concetti delle scienze etnoantropologiche",
            "raggruppamenti sociali",
            "sociologia della cultura"
        ],
        "domains": [
            "culture and society"
        ],
        "is_key_concept": true,
        "main_sense": ""
    },
    {
        "categories": [
            "comunit\u00e0 montane",
            "enti territoriali d'italia"
        ],
        "domains": [],
        "is_key_concept": false,
        "main_sense": ""
    }
]