[
    {
        "categories": [],
        "domains": [
            "culture and society"
        ],
        "is_key_concept": true,
        "main_sense": ""
    },
    {
        "categories": [
            "film commedia",
            "film diretti da larry buchanan",
            "film sexploitation",
            "film statunitensi del 1970"
        ],
        "domains": [
            "media"
        ],
        "is_key_concept": false,
        "main_sense": ""
    },
    {
        "categories": [],
        "domains": [],
        "is_key_concept": false,
        "main_sense": ""
    },
    {
        "categories": [
            "forme musicali",
            "generi teatrali",
            "opera"
        ],
        "domains": [
            "music"
        ],
        "is_key_concept": false,
        "main_sense": ""
    },
    {
        "categories": [],
        "domains": [],
        "is_key_concept": false,
        "main_sense": ""
    },
    {
        "categories": [],
        "domains": [],
        "is_key_concept": false,
        "main_sense": ""
    },
    {
        "categories": [],
        "domains": [
            "philosophy and psychology"
        ],
        "is_key_concept": false,
        "main_sense": ""
    },
    {
        "categories": [
            "strada",
            "strade"
        ],
        "domains": [
            "transport and travel"
        ],
        "is_key_concept": true,
        "main_sense": ""
    },
    {
        "categories": [
            "film commedia",
            "film diretti da larry buchanan",
            "film sexploitation",
            "film statunitensi del 1970"
        ],
        "domains": [
            "media"
        ],
        "is_key_concept": false,
        "main_sense": ""
    },
    {
        "categories": [],
        "domains": [],
        "is_key_concept": false,
        "main_sense": ""
    }
]