[
    {
        "categories": [],
        "domains": [
            "warfare and defense"
        ],
        "is_key_concept": false,
        "main_sense": ""
    },
    {
        "categories": [
            "pensiero critico",
            "professioni dello spettacolo"
        ],
        "domains": [
            "literature and theatre"
        ],
        "is_key_concept": false,
        "main_sense": ""
    },
    {
        "categories": [
            "gemme",
            "ossidi e idrossidi (minerali)"
        ],
        "domains": [
            "chemistry and mineralogy"
        ],
        "is_key_concept": false,
        "main_sense": ""
    },
    {
        "categories": [],
        "domains": [
            "philosophy and psychology"
        ],
        "is_key_concept": true,
        "main_sense": ""
    },
    {
        "categories": [],
        "domains": [
            "language and linguistics",
            "philosophy and psychology"
        ],
        "is_key_concept": false,
        "main_sense": ""
    }
]