[
    {
        "categories": [],
        "domains": [],
        "is_key_concept": false,
        "main_sense": ""
    },
    {
        "categories": [],
        "domains": [
            "politics and government"
        ],
        "is_key_concept": false,
        "main_sense": ""
    },
    {
        "categories": [],
        "domains": [],
        "is_key_concept": false,
        "main_sense": ""
    },
    {
        "categories": [
            "aristotele",
            "filosofi greci antichi del iv secolo a.c.",
            "logici greci antichi",
            "morti nel 322 a.c.",
            "nati a stagira",
            "personaggi citati nella divina commedia (inferno)",
            "scienziati greci antichi",
            "scolarchi del liceo"
        ],
        "domains": [
            "philosophy and psychology"
        ],
        "is_key_concept": false,
        "main_sense": ""
    }
]