[
    {
        "categories": [],
        "domains": [
            "philosophy and psychology"
        ],
        "is_key_concept": false,
        "main_sense": ""
    },
    {
        "categories": [
            "lingua italiana",
            "lingue svo"
        ],
        "domains": [
            "language and linguistics"
        ],
        "is_key_concept": false,
        "main_sense": ""
    },
    {
        "categories": [],
        "domains": [
            "business economics and finance"
        ],
        "is_key_concept": false,
        "main_sense": ""
    },
    {
        "categories": [
            "partiti liberali europei",
            "partiti politici europei",
            "repubblicanesimo"
        ],
        "domains": [
            "politics and government"
        ],
        "is_key_concept": false,
        "main_sense": ""
    },
    {
        "categories": [
            "grafica",
            "marca"
        ],
        "domains": [
            "business economics and finance"
        ],
        "is_key_concept": true,
        "main_sense": ""
    },
    {
        "categories": [],
        "domains": [],
        "is_key_concept": false,
        "main_sense": ""
    }
]