[
    {
        "categories": [
            "camere alte nazionali",
            "parlamento statunitense"
        ],
        "domains": [
            "politics and government"
        ],
        "is_key_concept": false,
        "main_sense": ""
    },
    {
        "categories": [],
        "domains": [],
        "is_key_concept": false,
        "main_sense": ""
    },
    {
        "categories": [
            "etica",
            "filosofia del diritto",
            "religione e politica"
        ],
        "domains": [
            "law and crime",
            "philosophy and psychology"
        ],
        "is_key_concept": false,
        "main_sense": ""
    },
    {
        "categories": [
            "cortometraggi drammatici",
            "cortometraggi muti statunitensi",
            "cortometraggi statunitensi del 1915"
        ],
        "domains": [
            "media"
        ],
        "is_key_concept": false,
        "main_sense": ""
    },
    {
        "categories": [],
        "domains": [],
        "is_key_concept": false,
        "main_sense": ""
    }
]