[
    {
        "categories": [],
        "domains": [
            "law and crime",
            "mathematics",
            "philosophy and psychology"
        ],
        "is_key_concept": true,
        "main_sense": ""
    },
    {
        "categories": [],
        "domains": [
            "physics and astronomy"
        ],
        "is_key_concept": false,
        "main_sense": ""
    },
    {
        "categories": [
            "disturbi dell'umore"
        ],
        "domains": [
            "health and medicine"
        ],
        "is_key_concept": false,
        "main_sense": ""
    },
    {
        "categories": [],
        "domains": [],
        "is_key_concept": false,
        "main_sense": ""
    },
    {
        "categories": [
            "federalismo"
        ],
        "domains": [
            "law and crime",
            "politics and government"
        ],
        "is_key_concept": false,
        "main_sense": ""
    }
]