[
    {
        "categories": [
            "elaborazione del linguaggio naturale",
            "filosofia del linguaggio",
            "logica"
        ],
        "domains": [
            "philosophy and psychology"
        ],
        "is_key_concept": true,
        "main_sense": ""
    },
    {
        "categories": [],
        "domains": [
            "mathematics",
            "games and video games",
            "sport and recreation"
        ],
        "is_key_concept": false,
        "main_sense": ""
    }
]