[
    {
        "categories": [],
        "domains": [
            "philosophy and psychology"
        ],
        "is_key_concept": false,
        "main_sense": ""
    },
    {
        "categories": [
            "operazioni finanziarie",
            "opzioni (finanza)"
        ],
        "domains": [
            "business economics and finance"
        ],
        "is_key_concept": false,
        "main_sense": ""
    },
    {
        "categories": [],
        "domains": [],
        "is_key_concept": false,
        "main_sense": ""
    },
    {
        "categories": [],
        "domains": [],
        "is_key_concept": false,
        "main_sense": ""
    },
    {
        "categories": [],
        "domains": [],
        "is_key_concept": false,
        "main_sense": ""
    },
    {
        "categories": [
            "chimica delle soluzioni",
            "concetti fondamentali di chimica"
        ],
        "domains": [
            "chemistry and mineralogy"
        ],
        "is_key_concept": true,
        "main_sense": ""
    },
    {
        "categories": [],
        "domains": [],
        "is_key_concept": false,
        "main_sense": ""
    },
    {
        "categories": [
            "libia"
        ],
        "domains": [],
        "is_key_concept": false,
        "main_sense": ""
    },
    {
        "categories": [
            "diari di viaggio",
            "opere di henry james",
            "opere letterarie del 1909",
            "opere letterarie in inglese"
        ],
        "domains": [
            "literature and theatre"
        ],
        "is_key_concept": false,
        "main_sense": ""
    },
    {
        "categories": [],
        "domains": [
            "business economics and finance"
        ],
        "is_key_concept": false,
        "main_sense": ""
    }
]