[
    {
        "categories": [],
        "domains": [],
        "is_key_concept": false,
        "main_sense": ""
    },
    {
        "categories": [],
        "domains": [
            "geography and places"
        ],
        "is_key_concept": false,
        "main_sense": ""
    },
    {
        "categories": [
            "assassinati con arma da fuoco",
            "martiri cattolici",
            "morti a trebisonda",
            "morti il 5 febbraio",
            "morti nel 2006",
            "nati a priverno",
            "nati il 7 settembre",
            "nati nel 1945",
            "parroci",
            "presbiteri italiani"
        ],
        "domains": [],
        "is_key_concept": false,
        "main_sense": ""
    },
    {
        "categories": [],
        "domains": [],
        "is_key_concept": false,
        "main_sense": ""
    },
    {
        "categories": [],
        "domains": [
            "law and crime"
        ],
        "is_key_concept": false,
        "main_sense": ""
    },
    {
        "categories": [],
        "domains": [],
        "is_key_concept": false,
        "main_sense": ""
    },
    {
        "categories": [],
        "domains": [],
        "is_key_concept": false,
        "main_sense": ""
    },
    {
        "categories": [
            "famiglia"
        ],
        "domains": [
            "biology"
        ],
        "is_key_concept": true,
        "main_sense": ""
    }
]