[
    {
        "categories": [],
        "domains": [],
        "is_key_concept": false,
        "main_sense": ""
    },
    {
        "categories": [],
        "domains": [],
        "is_key_concept": false,
        "main_sense": ""
    },
    {
        "categories": [
            "scuola"
        ],
        "domains": [
            "education"
        ],
        "is_key_concept": true,
        "main_sense": ""
    },
    {
        "categories": [
            "arte rinascimentale",
            "cultura a ferrara",
            "ferrara",
            "pittura italiana"
        ],
        "domains": [
            "art architecture and archaeology"
        ],
        "is_key_concept": false,
        "main_sense": ""
    },
    {
        "categories": [],
        "domains": [],
        "is_key_concept": false,
        "main_sense": ""
    },
    {
        "categories": [
            "concetti fondamentali di chimica",
            "reazioni chimiche"
        ],
        "domains": [
            "chemistry and mineralogy"
        ],
        "is_key_concept": true,
        "main_sense": ""
    },
    {
        "categories": [
            "delitti contro la libert\u00e0 morale",
            "diritto italiano"
        ],
        "domains": [
            "philosophy and psychology"
        ],
        "is_key_concept": false,
        "main_sense": ""
    }
]