[
    {
        "categories": [],
        "domains": [],
        "is_key_concept": false,
        "main_sense": ""
    },
    {
        "categories": [
            "ideologie politiche"
        ],
        "domains": [
            "politics and government"
        ],
        "is_key_concept": false,
        "main_sense": ""
    },
    {
        "categories": [],
        "domains": [],
        "is_key_concept": false,
        "main_sense": ""
    },
    {
        "categories": [],
        "domains": [
            "philosophy and psychology"
        ],
        "is_key_concept": false,
        "main_sense": ""
    },
    {
        "categories": [],
        "domains": [],
        "is_key_concept": false,
        "main_sense": ""
    },
    {
        "categories": [],
        "domains": [
            "physics and astronomy"
        ],
        "is_key_concept": false,
        "main_sense": ""
    },
    {
        "categories": [
            "ex aziende del gruppo fininvest",
            "periodici fondati nel 1974",
            "periodici in lingua italiana",
            "quotidiani italiani",
            "quotidiani politici"
        ],
        "domains": [
            "literature and theatre"
        ],
        "is_key_concept": false,
        "main_sense": ""
    },
    {
        "categories": [],
        "domains": [],
        "is_key_concept": false,
        "main_sense": ""
    }
]