[
    {
        "categories": [
            "ambiente",
            "festivit\u00e0 internazionali"
        ],
        "domains": [
            "physics and astronomy"
        ],
        "is_key_concept": false,
        "main_sense": ""
    },
    {
        "categories": [
            "ambiente",
            "festivit\u00e0 internazionali"
        ],
        "domains": [
            "physics and astronomy"
        ],
        "is_key_concept": false,
        "main_sense": ""
    },
    {
        "categories": [],
        "domains": [],
        "is_key_concept": false,
        "main_sense": ""
    }
]