[
    {
        "categories": [],
        "domains": [
            "biology"
        ],
        "is_key_concept": true,
        "main_sense": ""
    },
    {
        "categories": [
            "singoli certificati disco d'argento nel regno unito",
            "singoli certificati disco d'oro in italia",
            "singoli degli abba",
            "singoli del 1975",
            "singoli europop",
            "singoli glam rock",
            "singoli pop rock"
        ],
        "domains": [
            "music"
        ],
        "is_key_concept": false,
        "main_sense": ""
    },
    {
        "categories": [
            "storia"
        ],
        "domains": [
            "history"
        ],
        "is_key_concept": true,
        "main_sense": ""
    },
    {
        "categories": [
            "fillosilicati"
        ],
        "domains": [
            "chemistry and mineralogy"
        ],
        "is_key_concept": false,
        "main_sense": ""
    },
    {
        "categories": [
            "libro",
            "opere letterarie per tipo"
        ],
        "domains": [
            "literature and theatre"
        ],
        "is_key_concept": true,
        "main_sense": ""
    }
]