[
    {
        "categories": [],
        "domains": [
            "sport and recreation"
        ],
        "is_key_concept": false,
        "main_sense": ""
    },
    {
        "categories": [
            "architettura religiosa cristiana",
            "chiese"
        ],
        "domains": [
            "religion mysticism and mythology"
        ],
        "is_key_concept": true,
        "main_sense": ""
    },
    {
        "categories": [],
        "domains": [],
        "is_key_concept": false,
        "main_sense": ""
    },
    {
        "categories": [],
        "domains": [
            "biology"
        ],
        "is_key_concept": false,
        "main_sense": ""
    },
    {
        "categories": [],
        "domains": [
            "business economics and finance"
        ],
        "is_key_concept": true,
        "main_sense": ""
    },
    {
        "categories": [],
        "domains": [],
        "is_key_concept": false,
        "main_sense": ""
    },
    {
        "categories": [
            "grafica",
            "luce",
            "meccanica quantistica"
        ],
        "domains": [
            "physics and astronomy"
        ],
        "is_key_concept": true,
        "main_sense": ""
    },
    {
        "categories": [
            "acqua",
            "chimica degli alimenti",
            "composti dell'idrogeno",
            "fluidi"
        ],
        "domains": [
            "chemistry and mineralogy"
        ],
        "is_key_concept": true,
        "main_sense": ""
    },
    {
        "categories": [
            "fasi della materia",
            "fonti di riscaldamento",
            "gas"
        ],
        "domains": [
            "chemistry and mineralogy"
        ],
        "is_key_concept": true,
        "main_sense": ""
    }
]