[
    {
        "categories": [],
        "domains": [],
        "is_key_concept": false,
        "main_sense": ""
    },
    {
        "categories": [
            "antifascismo",
            "partigiani"
        ],
        "domains": [
            "warfare and defense"
        ],
        "is_key_concept": false,
        "main_sense": ""
    },
    {
        "categories": [],
        "domains": [],
        "is_key_concept": false,
        "main_sense": ""
    },
    {
        "categories": [
            "medaglistica",
            "oggetti di riconoscimento"
        ],
        "domains": [
            "heraldry honors and vexillology"
        ],
        "is_key_concept": true,
        "main_sense": ""
    },
    {
        "categories": [
            "valor militare"
        ],
        "domains": [
            "warfare and defense"
        ],
        "is_key_concept": false,
        "main_sense": ""
    },
    {
        "categories": [
            "valor militare"
        ],
        "domains": [
            "warfare and defense"
        ],
        "is_key_concept": false,
        "main_sense": ""
    }
]