[
    {
        "categories": [],
        "domains": [
            "art architecture and archaeology"
        ],
        "is_key_concept": false,
        "main_sense": ""
    },
    {
        "categories": [
            "piazze di roma",
            "roma r. iii colonna"
        ],
        "domains": [
            "geography and places"
        ],
        "is_key_concept": false,
        "main_sense": ""
    },
    {
        "categories": [],
        "domains": [
            "philosophy and psychology"
        ],
        "is_key_concept": false,
        "main_sense": ""
    },
    {
        "categories": [
            "diritto costituzionale",
            "governo",
            "stato"
        ],
        "domains": [
            "politics and government"
        ],
        "is_key_concept": true,
        "main_sense": ""
    }
]