[
    {
        "categories": [
            "etica",
            "teologia"
        ],
        "domains": [
            "religion mysticism and mythology",
            "philosophy and psychology"
        ],
        "is_key_concept": false,
        "main_sense": ""
    },
    {
        "categories": [],
        "domains": [
            "mathematics"
        ],
        "is_key_concept": false,
        "main_sense": ""
    },
    {
        "categories": [],
        "domains": [
            "culture and society"
        ],
        "is_key_concept": true,
        "main_sense": ""
    },
    {
        "categories": [
            "battaglie"
        ],
        "domains": [
            "warfare and defense"
        ],
        "is_key_concept": true,
        "main_sense": ""
    },
    {
        "categories": [],
        "domains": [],
        "is_key_concept": false,
        "main_sense": ""
    },
    {
        "categories": [],
        "domains": [
            "philosophy and psychology"
        ],
        "is_key_concept": true,
        "main_sense": ""
    },
    {
        "categories": [
            "fisica matematica",
            "matematica generale"
        ],
        "domains": [
            "mathematics"
        ],
        "is_key_concept": false,
        "main_sense": ""
    },
    {
        "categories": [],
        "domains": [],
        "is_key_concept": false,
        "main_sense": ""
    }
]