[
    {
        "categories": [
            "unit\u00e0 di misura astronomiche",
            "unit\u00e0 di tempo"
        ],
        "domains": [
            "physics and astronomy"
        ],
        "is_key_concept": false,
        "main_sense": ""
    },
    {
        "categories": [
            "battaglie navali dell'antica grecia",
            "impero achemenide",
            "salamina (isola)"
        ],
        "domains": [
            "warfare and defense",
            "history"
        ],
        "is_key_concept": false,
        "main_sense": ""
    },
    {
        "categories": [],
        "domains": [
            "animals"
        ],
        "is_key_concept": false,
        "main_sense": ""
    },
    {
        "categories": [],
        "domains": [],
        "is_key_concept": false,
        "main_sense": ""
    },
    {
        "categories": [
            "unit\u00e0 di misura astronomiche",
            "unit\u00e0 di tempo"
        ],
        "domains": [
            "physics and astronomy"
        ],
        "is_key_concept": false,
        "main_sense": ""
    },
    {
        "categories": [],
        "domains": [],
        "is_key_concept": false,
        "main_sense": ""
    },
    {
        "categories": [
            "componenti elettrici",
            "cordami",
            "industria tessile",
            "oggetti"
        ],
        "domains": [
            "engineering and technology"
        ],
        "is_key_concept": true,
        "main_sense": ""
    },
    {
        "categories": [
            "passato"
        ],
        "domains": [
            "physics and astronomy"
        ],
        "is_key_concept": true,
        "main_sense": ""
    }
]