[
    {
        "categories": [
            "gradi della scala"
        ],
        "domains": [
            "philosophy and psychology"
        ],
        "is_key_concept": true,
        "main_sense": ""
    },
    {
        "categories": [],
        "domains": [],
        "is_key_concept": false,
        "main_sense": ""
    },
    {
        "categories": [
            "mobili",
            "tavola"
        ],
        "domains": [
            "art architecture and archaeology"
        ],
        "is_key_concept": true,
        "main_sense": ""
    },
    {
        "categories": [
            "diritto costituzionale",
            "governo",
            "stato"
        ],
        "domains": [
            "politics and government"
        ],
        "is_key_concept": true,
        "main_sense": ""
    },
    {
        "categories": [],
        "domains": [
            "culture and society"
        ],
        "is_key_concept": true,
        "main_sense": ""
    },
    {
        "categories": [],
        "domains": [],
        "is_key_concept": false,
        "main_sense": ""
    },
    {
        "categories": [],
        "domains": [],
        "is_key_concept": false,
        "main_sense": ""
    },
    {
        "categories": [],
        "domains": [
            "health and medicine"
        ],
        "is_key_concept": false,
        "main_sense": ""
    }
]