[
    {
        "categories": [],
        "domains": [
            "biology"
        ],
        "is_key_concept": true,
        "main_sense": ""
    },
    {
        "categories": [
            "singoli certificati disco d'argento nel regno unito",
            "singoli certificati disco d'oro in italia",
            "singoli degli abba",
            "singoli del 1975",
            "singoli europop",
            "singoli glam rock",
            "singoli pop rock"
        ],
        "domains": [
            "music"
        ],
        "is_key_concept": false,
        "main_sense": ""
    },
    {
        "categories": [
            "concetti delle scienze etnoantropologiche",
            "concetti e principi filosofici",
            "teologia cristiana"
        ],
        "domains": [
            "biology"
        ],
        "is_key_concept": true,
        "main_sense": ""
    },
    {
        "categories": [],
        "domains": [
            "physics and astronomy"
        ],
        "is_key_concept": false,
        "main_sense": ""
    },
    {
        "categories": [],
        "domains": [],
        "is_key_concept": false,
        "main_sense": ""
    },
    {
        "categories": [],
        "domains": [],
        "is_key_concept": false,
        "main_sense": ""
    },
    {
        "categories": [
            "concetti e principi filosofici",
            "concetti e principi sul tempo"
        ],
        "domains": [
            "physics and astronomy"
        ],
        "is_key_concept": true,
        "main_sense": ""
    }
]