[
    {
        "categories": [],
        "domains": [],
        "is_key_concept": false,
        "main_sense": ""
    },
    {
        "categories": [
            "istituti di ricerca in italia"
        ],
        "domains": [],
        "is_key_concept": false,
        "main_sense": ""
    },
    {
        "categories": [
            "diritto civile",
            "immobiliare"
        ],
        "domains": [
            "business economics and finance",
            "law and crime"
        ],
        "is_key_concept": false,
        "main_sense": ""
    },
    {
        "categories": [],
        "domains": [],
        "is_key_concept": false,
        "main_sense": ""
    },
    {
        "categories": [],
        "domains": [
            "philosophy and psychology"
        ],
        "is_key_concept": false,
        "main_sense": ""
    },
    {
        "categories": [
            "diritto societario"
        ],
        "domains": [
            "business economics and finance"
        ],
        "is_key_concept": false,
        "main_sense": ""
    },
    {
        "categories": [
            "finanza aziendale",
            "macroeconomia",
            "ragioneria"
        ],
        "domains": [
            "business economics and finance"
        ],
        "is_key_concept": true,
        "main_sense": ""
    },
    {
        "categories": [
            "economia internazionale",
            "organizzazione mondiale del commercio"
        ],
        "domains": [
            "business economics and finance"
        ],
        "is_key_concept": false,
        "main_sense": ""
    },
    {
        "categories": [],
        "domains": [],
        "is_key_concept": false,
        "main_sense": ""
    },
    {
        "categories": [],
        "domains": [],
        "is_key_concept": false,
        "main_sense": ""
    },
    {
        "categories": [
            "fillosilicati"
        ],
        "domains": [
            "chemistry and mineralogy"
        ],
        "is_key_concept": false,
        "main_sense": ""
    }
]