[
    {
        "categories": [
            "europa"
        ],
        "domains": [],
        "is_key_concept": false,
        "main_sense": ""
    },
    {
        "categories": [],
        "domains": [],
        "is_key_concept": false,
        "main_sense": ""
    },
    {
        "categories": [],
        "domains": [],
        "is_key_concept": false,
        "main_sense": ""
    },
    {
        "categories": [],
        "domains": [
            "law and crime"
        ],
        "is_key_concept": false,
        "main_sense": ""
    },
    {
        "categories": [
            "bruxelles",
            "bruxelles-capitale"
        ],
        "domains": [
            "geography and places"
        ],
        "is_key_concept": false,
        "main_sense": ""
    },
    {
        "categories": [],
        "domains": [],
        "is_key_concept": false,
        "main_sense": ""
    },
    {
        "categories": [],
        "domains": [],
        "is_key_concept": false,
        "main_sense": ""
    },
    {
        "categories": [
            "partiti neonazisti e neofascisti",
            "partiti politici italiani"
        ],
        "domains": [],
        "is_key_concept": false,
        "main_sense": ""
    },
    {
        "categories": [],
        "domains": [
            "business economics and finance"
        ],
        "is_key_concept": false,
        "main_sense": ""
    },
    {
        "categories": [],
        "domains": [
            "politics and government"
        ],
        "is_key_concept": false,
        "main_sense": ""
    },
    {
        "categories": [],
        "domains": [],
        "is_key_concept": false,
        "main_sense": ""
    }
]