[
    {
        "categories": [],
        "domains": [
            "physics and astronomy"
        ],
        "is_key_concept": false,
        "main_sense": ""
    },
    {
        "categories": [],
        "domains": [
            "philosophy and psychology"
        ],
        "is_key_concept": false,
        "main_sense": ""
    },
    {
        "categories": [],
        "domains": [],
        "is_key_concept": false,
        "main_sense": ""
    },
    {
        "categories": [
            "nati ad assisi",
            "nati il 9 febbraio",
            "nati nel 1979",
            "politici del popolo della libert\u00e0",
            "politici di forza italia (1994)",
            "politici di forza italia (2013)",
            "politici italiani del xxi secolo",
            "politici italiani del xx secolo",
            "sindaci di perugia"
        ],
        "domains": [],
        "is_key_concept": false,
        "main_sense": ""
    },
    {
        "categories": [],
        "domains": [],
        "is_key_concept": false,
        "main_sense": ""
    },
    {
        "categories": [
            "unit\u00e0 di misura astronomiche",
            "unit\u00e0 di tempo"
        ],
        "domains": [
            "physics and astronomy"
        ],
        "is_key_concept": false,
        "main_sense": ""
    },
    {
        "categories": [
            "film ambientati nell'antica roma",
            "film comici",
            "film diretti da carlo vanzina",
            "film italiani del 1994"
        ],
        "domains": [],
        "is_key_concept": false,
        "main_sense": ""
    }
]